mqtt_hass_base/__init__.py
mqtt_hass_base/const.py
mqtt_hass_base/daemon.py
mqtt_hass_base/device.py
mqtt_hass_base/error.py
mqtt_hass_base/py.typed
mqtt_hass_base/entity/__init__.py
mqtt_hass_base/entity/binarysensor.py
mqtt_hass_base/entity/button.py
mqtt_hass_base/entity/common.py
mqtt_hass_base/entity/light.py
mqtt_hass_base/entity/lock.py
mqtt_hass_base/entity/number.py
mqtt_hass_base/entity/sensor.py
mqtt_hass_base/entity/switch.py
mqtt_hass_base/entity/vacuum.py
mqtt_hass_base-4.4.1.dist-info/licenses/LICENSE.txt
mqtt_hass_base-4.4.1.dist-info/METADATA
mqtt_hass_base-4.4.1.dist-info/WHEEL
mqtt_hass_base-4.4.1.dist-info/top_level.txt
mqtt_hass_base-4.4.1.dist-info/RECORD
