Metadata-Version: 2.4
Name: mqtt-hass-base
Version: 4.4.1
Summary: Bases to build mqtt daemon compatible with Home Assistant
Home-page: https://gitlab.com/ttblt-oss/hass/mqtt-hass-base
Author-email: Thibault Cohen <titilambert@gmail.com>
License: Apache-2.0
Project-URL: Source Code, https://gitlab.com/ttblt-oss/hass/mqtt_hass_base
Project-URL: Bug Reports, https://gitlab.com/ttblt-oss/hass/mqtt-hass-base/-/issues
Project-URL: Home-page, https://gitlab.com/ttblt-oss/hass/mqtt_hass_base
Keywords: homeassistant,mqtt,lib
Platform: any
Classifier: Programming Language :: Python :: 3
Classifier: License :: OSI Approved :: MIT License
Classifier: Operating System :: OS Independent
Requires-Python: >=3.12.0
License-File: LICENSE.txt
Requires-Dist: homeassistant==2025.11.1
Requires-Dist: aiomqtt==2.4.0
Dynamic: license-file
